{
    "判断题": {
        "网球比赛的分与分之间均有20秒的间歇时间；交换场地时，均有90秒的休息时间。": {
            "content": [],
            "answer": "错误"
        },
        "如果一名运动员发球次序有误，此错误发现时该局已经结束，则此局比分有效。": {
            "content": [],
            "answer": "正确"
        },
        "比赛开始前的准备活动时间，最多不能超过5分钟。": {
            "content": [],
            "answer": "正确"
        },
        "甲抽签获胜，选择发球，乙选择接发球。": {
            "content": [],
            "answer": "正确"
        },
        "比赛开始前的准备活动时间，最多不能超过15分钟。": {
            "content": [],
            "answer": "错误"
        },
        "比赛中，从上一分结束到下一分球被发出，之间的间隔时间不能超过20秒。": {
            "content": [],
            "answer": "错误"
        },
        "一名司线员呼报球出界，主裁判从球路来判断是界内球，因此他可以对司线员的判定作出改判。": {
            "content": [],
            "answer": "错误"
        },
        "主裁判判定重赛，而运动员认为不应该重赛，对此主裁判认为他的裁定是最终裁定。": {
            "content": [],
            "answer": "错误"
        },
        "裁判长可以在任何他认为有必要的时候，比如光线黑暗或场地条件或天气等原因而推延一场比赛。": {
            "content": [],
            "answer": "正确"
        },
        "无占先计分法，是指平分后双方加赛一分决定胜负；接发球的运动员可以选择他希望从场地的左半区接球还是从场地的右半区接球；获得决定分的运动员赢得该球。": {
            "content": [],
            "answer": "正确"
        },
        "获得四分同时领先对方两分为胜一局。": {
            "content": [],
            "answer": "正确"
        },
        "如果活球状态下的球落地后触到了永久固定物，击出该球的运动员赢得此分。": {
            "content": [],
            "answer": "正确"
        },
        "一名运动员站在场地的外面截击空中球，他将失分。": {
            "content": [],
            "answer": "错误"
        },
        "双打时，发球员发出的球直接触到了接球方队员或他所穿戴的或携带的任何物品，则发球员得分。": {
            "content": [],
            "answer": "正确"
        },
        "如果一盘结束后双方局数相加之和为双数时，则在下一盘第一局结束后再交换场地。": {
            "content": [],
            "answer": "正确"
        },
        "如果一名运动员发球次序有误，此错误发现时该局已经结束，则后面的发球次序仍然按照原来的次序进行。": {
            "content": [],
            "answer": "错误"
        },
        "运动员应该在每一盘的第一局、第三局和后面依此相错的局数结束后，以及每盘结束后双方所得局数之和为单数时交换场地。": {
            "content": [],
            "answer": "正确"
        },
        "双打比赛在任何一局中，当一方运动员发球次序发生错误，主裁判发觉后应立即纠正。发生错误前双方所的分数有效。": {
            "content": [],
            "answer": "正确"
        },
        "单打场地两个网柱间距离为10.06 米，网柱中心距同侧边线0.914 米。": {
            "content": [],
            "answer": "正确"
        },
        "在网球比赛中，对每一次新的伤害，运动员都可要求3分钟治疗，但不包括上一次治疗的伤害部位。": {
            "content": [],
            "answer": "正确"
        },
        "单打比赛在双打场地上进行，甲方扣杀后，衣服触及单打支柱以外的网球，裁判员应判为甲方失分。": {
            "content": [],
            "answer": "正确"
        },
        "为了重新将球抛高后发球，发球员用球拍接住已经被抛出的球，则该运动员失分 。": {
            "content": [],
            "answer": "错误"
        },
        "为了重新将球高抛后发球，发球员让已经抛出的球落到地面上，那么此发球员失分。": {
            "content": [],
            "answer": "错误"
        },
        "在正式比赛中，若双方选手在场上的比分为5：5时，则至少需要再打两局。": {
            "content": [],
            "answer": "正确"
        },
        "传统的东方式正手握拍击球的高度应该是在腰部的高度。": {
            "content": [],
            "answer": "正确"
        },
        "接发球运动员必须站在场地界线以内接球。": {
            "content": [],
            "answer": "错误"
        },
        "在单打比赛中，发球员不可以站在端线后单打边线与双打边线之间的位置发球。": {
            "content": [],
            "answer": "正确"
        },
        "如果一名运动员在发球时抛出两个以上的球而不是一个球时，那么这次发球应该判失误。": {
            "content": [],
            "answer": "错误"
        },
        "发球员的双脚不能触及端线后、中心标志与边线的假定延长线之间的区域以外的任何地方。": {
            "content": [],
            "answer": "正确"
        },
        "如果一名运动员发球次序有误，则应轮及发球的运动员在错误一被发现后就该立即发球，而在此错误发现前的比分均有效。": {
            "content": [],
            "answer": "正确"
        }
    },
    "单选题": {
        "罚分制是对违反运动员行为准则的运动员进行处罚的方法，具体分为：": {
            "content": [
                "A.警告，严重警告。",
                "\nB.警告，罚失一分。",
                "\nC.警告，罚失一分，罚失一局。",
                "\nD.警告，罚失一分，罚失一局，取消比赛资格。"
            ],
            "answer": "D"
        },
        "双打比赛中发球员发出的球擦网柱后并触及接球方网前运动员身体。裁判应判：": {
            "content": [
                "A.重发球。",
                "\nB.发球得分。",
                "\nC.发球失误。"
            ],
            "answer": "C"
        },
        "在国际网联男子巡回赛室外硬地比赛中，当下起小雨的时候，主裁判检查场地并发现球场上特别滑。然而看上去雨象是就要停了，而且场地也很快就可以使用了。此时主裁判应如何去做？": {
            "content": [
                "A.宣布：“暂停”，并允许运动员离开场地",
                "\nB.宣布：“暂停”，不允许运动员离开场地",
                "\nC.中止比赛，并要求运动员呆在场地上"
            ],
            "answer": "B"
        },
        "网球比赛中，第一发球失误后，捡球员很快将球拾起，并朝自己的位置跑去。而发球员没有等捡球员跑到位，便开始了他的第二次发球的动作。主裁判看到这种情况应如何处理？": {
            "content": [
                "A.如果发球员提出异议，则让其重发两次。",
                "\nB.无论如何都应重发两次。",
                "\nC.重发第二次发球。"
            ],
            "answer": "C"
        },
        "在网球女子单打比赛中，一名运动员在准备活动期间去了一次洗手间。他还可以去洗手间或更换衣服几次？": {
            "content": [
                "A.无。",
                "\nB.一次。",
                "\nC.两次。",
                "\nD.三次。"
            ],
            "answer": "B"
        },
        "网球比赛中，运动员在右区发球，虽然脚踩中点的假定延长线上，但在他挥拍击球时却提脚进入规定的区域，裁判应判": {
            "content": [
                "A.重发球",
                "\nB.脚误",
                "\nC.合法发球",
                "\nD.重赛"
            ],
            "answer": "B"
        },
        "在网球比赛进行中，有一个球滚入场内时该如何裁判": {
            "content": [
                "A.此时立刻停赛",
                "\nB.只有当球滚入本方区域的运动员可以叫重赛",
                "\nC.比赛继续",
                "\nD.双方运动员都应该立即要求重赛"
            ],
            "answer": "D"
        },
        "网球比赛中，球员不满司线员的判决,提出抗议,主裁应": {
            "content": [
                "A.可以改判",
                "\nB.询问司线员",
                "\nC.重赛",
                "\nD.维持原判"
            ],
            "answer": "D"
        },
        "网球比赛中，当一个明显出界的球被在底线后的运动员击了一下，应如何裁判：": {
            "content": [
                "A.此分重赛",
                "\nB.击此球的运动员失分",
                "\nC.接此球的运动员赢此分",
                "\nD.接住此球的运动员失分"
            ],
            "answer": "D"
        },
        "网球比赛中，发球时第一发球触网后，球未着地前触及接球员的衣服，应判": {
            "content": [
                "A.重发球",
                "\nB.重赛",
                "\nC.接球员失分",
                "\nD.发球员失分"
            ],
            "answer": "C"
        },
        "在2004年雅典奥运会上（_____ ）夺得网球女子双打金牌，是中国在奥运会上获得的第一块网球奖牌，为中国网球运动取得历史性突破。": {
            "content": [
                "A.郑洁与晏紫",
                "\nB.李婷与孙甜甜",
                "\nC.李婷与李娜",
                "\nD.郑洁与李婷"
            ],
            "answer": "B"
        },
        "男子网球选手新一代“天王”代表人物是（_____ ）。": {
            "content": [
                "A.桑普拉斯",
                "\nB.萨芬",
                "\nC.费德勒",
                "\nD.费雷罗"
            ],
            "answer": "C"
        },
        "在技术动作的产生过程中，最佳的生物力学的顺序依次为（_____ ）。": {
            "content": [
                "A.从身体小的部分到大的部分",
                "\nB.从身体大的部分到小的部分",
                "\nC.从身体正中的重心开始",
                "\nD.从头部往下开始"
            ],
            "answer": "B"
        },
        "在发球员踩线时，呼报为（_____ ）。": {
            "content": [
                "A.Out",
                "\nB.Fault",
                "\nC.FootFault",
                "\nD.FoulShot"
            ],
            "answer": "C"
        },
        "网球比赛的基本要素是（_____ ）。": {
            "content": [
                "A.角度、速度、高度",
                "\nB.速度、高度、深度",
                "\nC.深度、高度、角度",
                "\nD.角度、速度、深度"
            ],
            "answer": "D"
        },
        "发球时，（_____ ）为发球失误。": {
            "content": [
                "A.抛球后，球直接落在底线上",
                "\nB.一只脚越过底线",
                "\nC.击球的瞬间，双脚同时跃起",
                "\nD.挥拍后未击中球，但同时用手接住球"
            ],
            "answer": "D"
        },
        "球网中间的高度是（_____ ）米。": {
            "content": [
                "A.0.914",
                "\nB.1.07",
                "\nC.1.115",
                "\nD.1.37"
            ],
            "answer": "A"
        },
        "网球场地的单打边线长度是（_____）米。": {
            "content": [
                "A.23.77",
                "\nB.21.52",
                "\nC.11.885",
                "\nD.8.23"
            ],
            "answer": "A"
        },
        "国际标准网球场边线外空地至少有（_____ ）米。": {
            "content": [
                "A.8.23",
                "\nB.6.40",
                "\nC.3.66",
                "\nD.1.07"
            ],
            "answer": "C"
        }
    },
    "多选题": {}
}